tap/__init__.py
tap/tap.py
taplib-0.1.8.dist-info/LICENSE
taplib-0.1.8.dist-info/METADATA
taplib-0.1.8.dist-info/WHEEL
taplib-0.1.8.dist-info/top_level.txt
taplib-0.1.8.dist-info/RECORD
