Metadata-Version: 2.2
Name: taplib
Version: 0.1.8
Summary: Python package to make statistical test and add statistical annotations on plots generated with Plotly
Author: Federica Persiani, Damiano Malori
Project-URL: Homepage, https://github.com/Discovery-Circle/tap
Project-URL: Issues, https://github.com/Discovery-Circle/tap/issues
Classifier: Programming Language :: Python :: 3.10
Classifier: License :: OSI Approved :: MIT License
Classifier: Operating System :: OS Independent
Requires-Python: >=3.10
License-File: LICENSE
Requires-Dist: statsmodels>=0.13.5
Requires-Dist: scipy>=1.10.0
Requires-Dist: plotly>=5.15.0
Requires-Dist: nbformat>=4.2.0
Requires-Dist: scikit-posthocs>=0.8.0
Requires-Dist: kaleido==0.1.0.post1; platform_system == "Windows"
Requires-Dist: kaleido>=0.1.0; platform_system != "Windows"
